{
  "symbol": "BTCUSDT",
  "timeframe": "1m",
  "start_date": "2020-12-12T18:08:11.375628",
  "end_date": "2025-12-11T18:08:11.375628",
  "total_candles": 2626615,
  "total_signals": 87603,
  "total_trades": 87603,
  "wins": 37251,
  "losses": 50352,
  "win_rate": 42.52251635217972,
  "profit_factor": 1.0768851386846654,
  "total_pnl_pct": 389.47791673182746,
  "avg_win_pct": 0.14644410159113413,
  "avg_loss_pct": -0.100605960272471,
  "max_drawdown_pct": 60.24992401401725,
  "long_trades": 43397,
  "long_win_rate": 42.196465193446556,
  "short_trades": 44206,
  "short_win_rate": 42.842600551961276,
  "trades": [
    {
      "timestamp": 1607799719999,
      "direction": "LONG",
      "entry_price": 18705.71,
      "exit_price": 18727.7806573857,
      "stop_loss": 18690.99622840953,
      "take_profit": 18727.7806573857,
      "pnl_pct": 0.1179888781858714,
      "is_win": 